{"assets":{"9FCFE3BE7EA7F92873E9F97E62D69A8C":{"type":"texture","index":0,"assetRequest":{"type":"slide","state":"contents","slide":"none"},"url":{"native":"assets/24D29C4E-C87D-48F6-BB97-FB8C210F55DE.pdf"},"width":1024,"height":768},"3AC15AB3F2FBC7987E7E763BFE85EE15":{"type":"texture","index":1,"assetRequest":{"type":"slide","state":"contents","slide":"none"},"url":{"native":"assets/24D29C4E-C87D-48F6-BB97-FB8C210F55DE.pdf"},"width":1024,"height":768}},"events":[{"effects":[{"beginTime":0,"baseLayer":{"animations":[],"initialState":{"affineTransform":[1,0,0,1,0,0],"masksToBounds":false,"rotation":0,"scale":1,"position":{"pointX":512,"pointY":384},"width":1024,"sublayerTransform":[1,0,0,0,0,1,0,0,0,0,1,0,0,0,0,1],"contentsRect":{"y":0,"x":0,"width":1,"height":1},"opacity":1,"edgeAntialiasingMask":251658240,"height":768,"hidden":false,"anchorPoint":{"pointX":0.5,"pointY":0.5}},"objectID":"0","layers":[{"animations":[],"initialState":{"affineTransform":[1,0,0,1,0,0],"masksToBounds":false,"rotation":0,"scale":1,"position":{"pointX":512,"pointY":384},"width":1024,"sublayerTransform":[1,0,0,0,0,1,0,0,0,0,1,-0.0004922987690640373,0,0,0,1],"contentsRect":{"y":0,"x":0,"width":1,"height":1},"opacity":1,"edgeAntialiasingMask":251658240,"height":768,"hidden":false,"anchorPoint":{"pointX":0.5,"pointY":0.5}},"layers":[{"animations":[],"layers":[],"texturedRectangle":{"isBackgroundTexture":false,"singleTextureOpacity":1,"textureType":0,"textBaseline":0,"textXHeight":0,"isVerticalText":false},"initialState":{"affineTransform":[1,0,0,1,0,0],"masksToBounds":false,"rotation":0,"scale":1,"position":{"pointX":512,"pointY":384},"width":1024,"sublayerTransform":[1,0,0,0,0,1,0,0,0,0,1,0,0,0,0,1],"contentsRect":{"y":0,"x":0,"width":1,"height":1},"opacity":1,"edgeAntialiasingMask":0,"height":768,"hidden":false,"anchorPoint":{"pointX":0.5,"pointY":0.5}},"texture":"3AC15AB3F2FBC7987E7E763BFE85EE15"},{"animations":[{"timeOffset":0,"from":{"scalar":false},"beginTime":0,"repeatCount":0,"fillMode":"both","property":"hidden","autoreverses":false,"duration":0.01,"to":{"scalar":true}}],"layers":[],"texturedRectangle":{"isBackgroundTexture":false,"singleTextureOpacity":1,"textureType":0,"textBaseline":0,"textXHeight":0,"isVerticalText":false},"initialState":{"affineTransform":[1,0,0,1,0,0],"masksToBounds":false,"rotation":0,"scale":1,"position":{"pointX":512,"pointY":384},"width":1024,"sublayerTransform":[1,0,0,0,0,1,0,0,0,0,1,0,0,0,0,1],"contentsRect":{"y":0,"x":0,"width":1,"height":1},"opacity":1,"edgeAntialiasingMask":0,"height":768,"hidden":false,"anchorPoint":{"pointX":0.5,"pointY":0.5}},"texture":"9FCFE3BE7EA7F92873E9F97E62D69A8C"}]}]},"effects":[],"duration":0.01,"type":"transition","name":"none","objectID":"0"}],"automaticPlay":false,"hyperlinks":[],"accessibility":[{"text":"gap","targetRectangle":{"y":571.9514770507812,"x":31.4419342223989,"width":71.85599999999999,"height":42}},{"text":"What’s been done?","targetRectangle":{"y":254,"x":114,"width":276.256,"height":37.10400390625}},{"text":"Boudin et al. [11], Schardt et al. [71], and Hoogendam et al. [32] incorporate clinical labels (PICO) into query formulation","targetRectangle":{"y":292,"x":149,"width":780.288,"height":156.10400390625}},{"text":"What’s the gap?","targetRectangle":{"y":449,"x":114,"width":232.384,"height":79.10400390625}},{"text":"Ad-hoc experiments, only incorporate PICO into query formulation, do not consider documents","targetRectangle":{"y":529,"x":149,"width":791.808,"height":119.07177734375}},{"text":"[11] Florian Boudin, Jian-Yun Nie, and Martin Dawes. Clinical information retrieval using document and pico structure. In Human Language Technologies: The 2010 Annual Conference of the North American Chapter of the Association for Computational Linguistics, pages 822–830. Association for Computational Linguistics, 2010. ","targetRectangle":{"y":667.0000021457672,"x":21.2924633026123,"width":949.0693359375,"height":23}},{"text":"[71] Connie Schardt, Martha B Adams, Thomas Owens, Sheri Keitz, and Paul Fontelo. Utilization of the pico framework to improve searching pubmed for clinical questions. BMC Medical Informatics and Decision Making, 7(1):16, 2007. ","targetRectangle":{"y":690.0000021457672,"x":21.2924633026123,"width":933.96533203125,"height":12}},{"text":"[32] Arjen Hoogendam, Pieter F de Vries Robbe, and A John PM Overbeke. Comparing patient characteristics, type of intervention, control, and outcome (pico) queries with unguided searching: a randomized controlled crossover trial ec. Journal of the Medical Library Association, 100(2):121, 2012. ","targetRectangle":{"y":702.0000021457672,"x":21.2924633026123,"width":981.580078125,"height":22}},{"text":"￼","targetRectangle":{"y":736,"x":502.8373380303383,"width":17.79200000000003,"height":17.535888671875}},{"text":"Beyond Boolean","targetRectangle":{"y":72,"x":332.263671875,"width":359.47265625,"height":66}}],"baseLayer":{"animations":[],"initialState":{"affineTransform":[1,0,0,1,0,0],"masksToBounds":false,"rotation":0,"scale":1,"position":{"pointX":512,"pointY":384},"width":1024,"sublayerTransform":[1,0,0,0,0,1,0,0,0,0,1,0,0,0,0,1],"contentsRect":{"y":0,"x":0,"width":1,"height":1},"opacity":1,"edgeAntialiasingMask":251658240,"height":768,"hidden":false,"anchorPoint":{"pointX":0.5,"pointY":0.5}},"objectID":"0","layers":[{"animations":[],"initialState":{"affineTransform":[1,0,0,1,0,0],"masksToBounds":false,"rotation":0,"scale":1,"position":{"pointX":512,"pointY":384},"width":1024,"sublayerTransform":[1,0,0,0,0,1,0,0,0,0,1,-0.0004922987690640373,0,0,0,1],"contentsRect":{"y":0,"x":0,"width":1,"height":1},"opacity":1,"edgeAntialiasingMask":251658240,"height":768,"hidden":false,"anchorPoint":{"pointX":0.5,"pointY":0.5}},"layers":[{"animations":[],"layers":[],"texturedRectangle":{"isBackgroundTexture":false,"singleTextureOpacity":1,"textureType":0,"textBaseline":0,"textXHeight":0,"isVerticalText":false},"initialState":{"affineTransform":[1,0,0,1,0,0],"masksToBounds":false,"rotation":0,"scale":1,"position":{"pointX":512,"pointY":384},"width":1024,"sublayerTransform":[1,0,0,0,0,1,0,0,0,0,1,0,0,0,0,1],"contentsRect":{"y":0,"x":0,"width":1,"height":1},"opacity":1,"edgeAntialiasingMask":0,"height":768,"hidden":false,"anchorPoint":{"pointX":0.5,"pointY":0.5}},"texture":"9FCFE3BE7EA7F92873E9F97E62D69A8C"}]}]}}]}